src/__init__.py
src/_version.py
src/list.py
src/localgit.py
src/log.py
src/parsers.py
src/pretty_print.py
src/pull.py
src/push.py
src/status.py
src/utils.py
localgit-1.1.1.dist-info/LICENSE
localgit-1.1.1.dist-info/METADATA
localgit-1.1.1.dist-info/WHEEL
localgit-1.1.1.dist-info/entry_points.txt
localgit-1.1.1.dist-info/top_level.txt
localgit-1.1.1.dist-info/RECORD
