Metadata-Version: 2.1
Name: localgit
Version: 1.1.1
Summary: localgit is a CL tool for managing multiple local git repo clones simultaneously.
Home-page: https://github.com/natibek/localgit/tree/main
Author: Nathnael Bekele
Author-email: nwtbekele@gmail.com
License: Apache 2.0
Classifier: Development Status :: 4 - Beta
Classifier: License :: OSI Approved :: Apache Software License
Classifier: Programming Language :: Python :: 3
Classifier: Operating System :: OS Independent
Requires-Python: >=3.11.0
License-File: LICENSE
